MANIFEST.in
README.rst
requirements.txt
setup.py
test-requirements.txt
yaprt/__init__.py
yaprt/clone_repos.py
yaprt/data_process.py
yaprt/executable.py
yaprt/html_indexer.py
yaprt/packaging_report.py
yaprt/utils.py
yaprt/wheel_builder.py
yaprt.egg-info/PKG-INFO
yaprt.egg-info/SOURCES.txt
yaprt.egg-info/dependency_links.txt
yaprt.egg-info/entry_points.txt
yaprt.egg-info/pbr.json
yaprt.egg-info/requires.txt
yaprt.egg-info/top_level.txt