Metadata-Version: 1.1
Name: yaprt
Version: 0.4.1
Summary: Repository builder for python source code
Home-page: https://github.com/cloudnull/yaprt.git
Author: Kevin Carter
Author-email: kevin.carter@rackspace.com
License: License :: OSI Approved :: Apache Software License
Platform: UNKNOWN
Classifier: Development Status :: 5 - Production/Stable
Classifier: Intended Audience :: Information Technology
Classifier: Intended Audience :: System Administrators
Classifier: Intended Audience :: Developers
Classifier: Operating System :: OS Independent
Classifier: License :: OSI Approved :: Apache Software License
Classifier: Programming Language :: Python :: 2.6
Classifier: Programming Language :: Python :: 2.7
Classifier: Topic :: Utilities
Classifier: Topic :: Software Development :: Libraries :: Python Modules
